README.md
setup.py
nc5ng/gmt/__init__.py
nc5ng/gmt/options.py
nc5ng/gmt/plotter.py
nc5ng/types/__init__.py
nc5ng/types/_abc.py
nc5ng/types/datapoint.py
nc5ng/types/parsers.py
nc5ng_common.egg-info/PKG-INFO
nc5ng_common.egg-info/SOURCES.txt
nc5ng_common.egg-info/dependency_links.txt
nc5ng_common.egg-info/requires.txt
nc5ng_common.egg-info/top_level.txt