Metadata-Version: 1.1
Name: nc5ng-common
Version: 0.0.4.post1
Summary: Python common packages for nc5ng
Home-page: https://nc5ng.org/projects/nc5ng-python
Author: Andrey Shmakov
Author-email: akshmakov@gmail.com
License: MIT
Download-URL: https://github.com/nc5ng/nc5ng-python-common
Platform: UNKNOWN
